cflearn/__init__.py
cflearn/constants.py
cflearn/pipeline.py
cflearn/protocol.py
cflearn/trainer.py
cflearn/types.py
cflearn/api/__init__.py
cflearn/api/interface.py
cflearn/api/register.py
cflearn/api/cv/__init__.py
cflearn/api/cv/interface.py
cflearn/api/cv/pipeline.py
cflearn/api/cv/data/__init__.py
cflearn/api/cv/data/interface.py
cflearn/api/cv/data/models/__init__.py
cflearn/api/cv/data/models/style_transfer.py
cflearn/api/cv/data/transforms/A.py
cflearn/api/cv/data/transforms/__init__.py
cflearn/api/cv/data/transforms/general.py
cflearn/api/cv/data/transforms/interface.py
cflearn/api/cv/data/transforms/pt.py
cflearn/api/cv/models/__init__.py
cflearn/api/cv/models/dino.py
cflearn/api/cv/models/vq_vae.py
cflearn/api/dl/__init__.py
cflearn/api/dl/pipeline.py
cflearn/api/ml/__init__.py
cflearn/api/ml/interface.py
cflearn/api/ml/pipeline.py
cflearn/api/ml/models/__init__.py
cflearn/api/ml/models/ddr.py
cflearn/api/multimodal/__init__.py
cflearn/api/multimodal/models/__init__.py
cflearn/api/multimodal/models/aligner/__init__.py
cflearn/api/multimodal/models/aligner/clip_vqgan.py
cflearn/api/zoo/__init__.py
cflearn/api/zoo/core.py
cflearn/api/zoo/configs/clf/cct/default.json
cflearn/api/zoo/configs/clf/cct/large.json
cflearn/api/zoo/configs/clf/cct/large_224.json
cflearn/api/zoo/configs/clf/cct/large_384.json
cflearn/api/zoo/configs/clf/cct/lite.json
cflearn/api/zoo/configs/clf/resnet101/default.json
cflearn/api/zoo/configs/clf/resnet18/default.json
cflearn/api/zoo/configs/clf/resnet18/gray.json
cflearn/api/zoo/configs/gan/siren/default.json
cflearn/api/zoo/configs/gan/siren/gray.json
cflearn/api/zoo/configs/gan/vanilla/default.json
cflearn/api/zoo/configs/gan/vanilla/gray.json
cflearn/api/zoo/configs/generator/cycle_gan_generator/default.json
cflearn/api/zoo/configs/generator/pixel_cnn/default.json
cflearn/api/zoo/configs/generator/style_gan2_generator/1024.json
cflearn/api/zoo/configs/generator/style_gan2_generator/default.json
carefree_learn-0.2.1.dist-info/LICENSE
carefree_learn-0.2.1.dist-info/METADATA
carefree_learn-0.2.1.dist-info/WHEEL
carefree_learn-0.2.1.dist-info/top_level.txt
carefree_learn-0.2.1.dist-info/RECORD
