Metadata-Version: 2.1
Name: carefree-learn
Version: 0.2.1
Summary: Deep Learning with PyTorch made easy
Home-page: https://github.com/carefree0910/carefree-learn
Author: carefree0910
Author-email: syameimaru.saki@gmail.com
License: UNKNOWN
Download-URL: https://github.com/carefree0910/carefree-learn/archive/v0.2.1.tar.gz
Keywords: python machine-learning deep-learning solution PyTorch
Platform: UNKNOWN
License-File: LICENSE
Requires-Dist: ftfy
Requires-Dist: regex
Requires-Dist: lmdb
Requires-Dist: einops
Requires-Dist: albumentations
Requires-Dist: scikit-image
Requires-Dist: numba (>=0.50)
Requires-Dist: mlflow
Requires-Dist: onnx
Requires-Dist: onnx-simplifier
Requires-Dist: onnxruntime
Requires-Dist: plotly
Requires-Dist: carefree-data (>=0.2.5)
Requires-Dist: carefree-toolkit (>=0.2.8)
Requires-Dist: dill
Requires-Dist: future
Requires-Dist: psutil
Requires-Dist: cython (>=0.29.12)
Requires-Dist: numpy (>=1.19.2)
Requires-Dist: scipy (>=1.2.1)
Requires-Dist: scikit-learn (>=0.23.1)
Requires-Dist: matplotlib (>=3.0.3)
